__init__.py
sdo.py
setup.py
testsdo.py
sdo.egg-info/PKG-INFO
sdo.egg-info/SOURCES.txt
sdo.egg-info/dependency_links.txt
sdo.egg-info/requires.txt
sdo.egg-info/top_level.txt