Metadata-Version: 1.0
Name: sdo
Version: 0.6.4
Summary: Converts oracle SDO_GEOMETRY objects to WKT and GeoJSON.
Home-page: UNKNOWN
Author: tib00r
Author-email: tibor.arpas@infinit.sk
License: UNKNOWN
Platform: UNKNOWN
Classifier: D
Classifier: e
Classifier: v
Classifier: e
Classifier: l
Classifier: o
Classifier: p
Classifier: m
Classifier: e
Classifier: n
Classifier: t
Classifier:  
Classifier: S
Classifier: t
Classifier: a
Classifier: t
Classifier: u
Classifier: s
Classifier:  
Classifier: :
Classifier: :
Classifier:  
Classifier: 4
Classifier:  
Classifier: -
Classifier:  
Classifier: B
Classifier: e
Classifier: t
Classifier: a
